pyoliteutils/__init__.py
pyoliteutils/_version.py
pyoliteutils/info.py
pyoliteutils/kroki.py
pyoliteutils/lessonsurvey.py
pyoliteutils/mermaid.py
pyoliteutils/pyoliteutils.py
pyoliteutils/wordcloud.py
pyoliteutils-0.0.17.dist-info/LICENSE
pyoliteutils-0.0.17.dist-info/METADATA
pyoliteutils-0.0.17.dist-info/WHEEL
pyoliteutils-0.0.17.dist-info/top_level.txt
pyoliteutils-0.0.17.dist-info/RECORD
