Metadata-Version: 2.1
Name: pyoliteutils
Version: 0.0.17
Summary: Utils for making pyolite easier to use inside MS Teams notebooks.
Author: Marty Eggleton @ UTC Sheffield OLP
Author-email: meggleton@utcsheffield.org.uk
Classifier: Programming Language :: Python :: 3
Classifier: License :: OSI Approved :: MIT License
Classifier: Operating System :: OS Independent
Requires-Python: >=3.6
License-File: LICENSE
Requires-Dist: matplotlib
Requires-Dist: pandas
